{
  "rook_graph_report": {
    "number_of_nodes": 1448,
    "number_of_edges": 4020,
    "degree_statistics": {
      "counts": {
        "4": 303,
        "5": 374,
        "10": 31,
        "8": 80,
        "7": 171,
        "6": 288,
        "3": 111,
        "15": 2,
        "9": 45,
        "2": 19,
        "12": 4,
        "11": 12,
        "18": 1,
        "13": 6,
        "1": 1
      },
      "min": 1,
      "max": 18,
      "mean": 5.552,
      "median": 5.0,
      "variance": 3.497
    },
    "connected_components": 1,
    "units_entirely_contained_in_another": [],
    "number_of_units_entirely_contained_in_another": 0,
    "eigenvalues_histogram": {
      "bins": [
        [
          -0.0,
          0.776
        ],
        [
          0.776,
          1.551
        ],
        [
          1.551,
          2.327
        ],
        [
          2.327,
          3.102
        ],
        [
          3.102,
          3.878
        ],
        [
          3.878,
          4.653
        ],
        [
          4.653,
          5.429
        ],
        [
          5.429,
          6.204
        ],
        [
          6.204,
          6.98
        ],
        [
          6.98,
          7.755
        ],
        [
          7.755,
          8.531
        ],
        [
          8.531,
          9.306
        ],
        [
          9.306,
          10.082
        ],
        [
          10.082,
          10.857
        ],
        [
          10.857,
          11.633
        ],
        [
          11.633,
          12.408
        ],
        [
          12.408,
          13.184
        ],
        [
          13.184,
          13.959
        ],
        [
          13.959,
          14.735
        ],
        [
          14.735,
          15.51
        ],
        [
          15.51,
          16.286
        ],
        [
          16.286,
          17.061
        ],
        [
          17.061,
          17.837
        ],
        [
          17.837,
          18.612
        ],
        [
          18.612,
          19.388
        ]
      ],
      "counts": [
        70,
        82,
        90,
        108,
        95,
        116,
        141,
        136,
        144,
        135,
        103,
        80,
        50,
        36,
        28,
        13,
        8,
        4,
        6,
        0,
        1,
        1,
        0,
        0,
        1
      ]
    }
  },
  "queen_graph_report": {
    "number_of_nodes": 1448,
    "number_of_edges": 4466,
    "degree_statistics": {
      "counts": {
        "4": 189,
        "5": 290,
        "10": 49,
        "8": 129,
        "7": 237,
        "6": 333,
        "3": 81,
        "9": 76,
        "15": 4,
        "2": 15,
        "16": 1,
        "11": 22,
        "12": 10,
        "20": 1,
        "13": 9,
        "14": 1,
        "1": 1
      },
      "min": 1,
      "max": 20,
      "mean": 6.169,
      "median": 6.0,
      "variance": 4.323
    },
    "connected_components": 1,
    "units_entirely_contained_in_another": [],
    "number_of_units_entirely_contained_in_another": 0,
    "eigenvalues_histogram": {
      "bins": [
        [
          0.0,
          0.791
        ],
        [
          0.791,
          1.582
        ],
        [
          1.582,
          2.373
        ],
        [
          2.373,
          3.164
        ],
        [
          3.164,
          3.955
        ],
        [
          3.955,
          4.746
        ],
        [
          4.746,
          5.537
        ],
        [
          5.537,
          6.328
        ],
        [
          6.328,
          7.119
        ],
        [
          7.119,
          7.91
        ],
        [
          7.91,
          8.701
        ],
        [
          8.701,
          9.492
        ],
        [
          9.492,
          10.283
        ],
        [
          10.283,
          11.074
        ],
        [
          11.074,
          11.865
        ],
        [
          11.865,
          12.656
        ],
        [
          12.656,
          13.447
        ],
        [
          13.447,
          14.238
        ],
        [
          14.238,
          15.029
        ],
        [
          15.029,
          15.82
        ],
        [
          15.82,
          16.611
        ],
        [
          16.611,
          17.402
        ],
        [
          17.402,
          18.194
        ],
        [
          18.194,
          18.985
        ],
        [
          18.985,
          19.776
        ],
        [
          19.776,
          20.567
        ],
        [
          20.567,
          21.358
        ]
      ],
      "counts": [
        60,
        69,
        81,
        89,
        89,
        98,
        127,
        124,
        133,
        148,
        121,
        90,
        74,
        51,
        35,
        27,
        8,
        9,
        8,
        1,
        3,
        2,
        0,
        0,
        0,
        0,
        1
      ]
    }
  },
  "comparison": {
    "rook_vs_queen_comparison": {
      "number_of_rook_edges": 4020,
      "number_of_queen_edges": 4466,
      "common_edges": 4020,
      "symmetric_difference": 446,
      "percent_common": 0.9
    }
  }
}